fast_tcrdist/__init__.py
fast_tcrdist/aggregate_data.py
fast_tcrdist/plot.py
fast_tcrdist/useful.py
fast_tcrdist/tcrdist/__init__.py
fast_tcrdist/tcrdist/create_datasets.py
fast_tcrdist/tcrdist/stats.py
fast_tcrdist/tcrdist/v_gene_distances.py
fast_tcrdist/tcrdist/cython/BLOSUM62
fast_tcrdist/tcrdist/cython/__init__.py
fast_tcrdist/tcrdist/cython/blosum_mtx.py
fast_tcrdist/tcrdist/cython/cnwalign.c
fast_tcrdist/tcrdist/cython/cnwalign.cp37-win_amd64.pyd
fast_tcrdist/tcrdist/cython/seq_dist.c
fast_tcrdist/tcrdist/cython/seq_dist.cp37-win_amd64.pyd
fast_tcrdist/tcrdist/db/__init__.py
fast_tcrdist/tcrdist/db/adj_blosum.json
fast_tcrdist/tcrdist/db/blosum.json
fast_tcrdist/tcrdist/db/human_cdrs_for_10X.json
fast_tcrdist/tcrdist/db/human_v_gene_dists.json
fast_tcrdist/tcrdist/db/mouse_cdrs_for_10X.json
fast_tcrdist/tcrdist/db/mouse_v_gene_dists.json
fast_tcrdist-0.0.3.dist-info/LICENSE
fast_tcrdist-0.0.3.dist-info/METADATA
fast_tcrdist-0.0.3.dist-info/WHEEL
fast_tcrdist-0.0.3.dist-info/top_level.txt
fast_tcrdist-0.0.3.dist-info/RECORD
